yt_grabber/__init__.py
yt_grabber/batch.py
yt_grabber/cli.py
yt_grabber/config.py
yt_grabber/downloader.py
yt_grabber/models.py
yt_grabber/notifier.py
yt_grabber/playlist.py
yt_grabber/playlist_header.py
yt_grabber/playlist_manager.py
yt_grabber/sync.py
yt_grabber/extractors/__init__.py
yt_grabber/extractors/base.py
yt_grabber/extractors/channel.py
yt_grabber/extractors/playlist.py
yt_grabber-0.3.2.dist-info/METADATA
yt_grabber-0.3.2.dist-info/WHEEL
yt_grabber-0.3.2.dist-info/entry_points.txt
yt_grabber-0.3.2.dist-info/licenses/LICENSE
yt_grabber-0.3.2.dist-info/RECORD
