Metadata-Version: 2.4
Name: yt-grabber
Version: 0.3.2
Summary: A CLI tool for downloading videos from YT playlists and channels
Project-URL: Repository, https://github.com/elisey/yt-grabber
Project-URL: Issues, https://github.com/elisey/yt-grabber/issues
Author: Elisei
License: MIT
License-File: LICENSE
Keywords: cli,downloader,media,playlist,video,yt-dlp
Classifier: Development Status :: 4 - Beta
Classifier: Environment :: Console
Classifier: Intended Audience :: End Users/Desktop
Classifier: License :: OSI Approved :: MIT License
Classifier: Operating System :: OS Independent
Classifier: Programming Language :: Python :: 3
Classifier: Programming Language :: Python :: 3.12
Classifier: Programming Language :: Python :: 3.13
Classifier: Programming Language :: Python :: 3.14
Classifier: Topic :: Multimedia :: Video
Requires-Python: >=3.12
Requires-Dist: loguru>=0.7.3
Requires-Dist: pydantic-settings>=2.12.0
Requires-Dist: python-telegram-bot>=21.0
Requires-Dist: typer>=0.21.1
Requires-Dist: yt-dlp>=2025.12.8
Provides-Extra: dev
Requires-Dist: pytest-asyncio>=0.23.0; extra == 'dev'
Requires-Dist: pytest-cov>=4.1.0; extra == 'dev'
Requires-Dist: pytest-mock>=3.12.0; extra == 'dev'
Requires-Dist: pytest>=8.0.0; extra == 'dev'
